public class de.viadee.lambda.codebeispiele.sprachAenderungen.LambdaVsInnerClass2 {
  public de.viadee.lambda.codebeispiele.sprachAenderungen.LambdaVsInnerClass2();
    Code:
       0: aload_0
       1: invokespecial #8                  // Method java/lang/Object."<init>":()V
       4: return

  public static void main(java.lang.String[]);
    Code:
       0: iconst_4
       1: anewarray     #16                 // class java/lang/Integer
       4: dup
       5: iconst_0
       6: iconst_2
       7: invokestatic  #18                 // Method java/lang/Integer.valueOf:(I)Ljava/lang/Integer;
      10: aastore
      11: dup
      12: iconst_1
      13: iconst_5
      14: invokestatic  #18                 // Method java/lang/Integer.valueOf:(I)Ljava/lang/Integer;
      17: aastore
      18: dup
      19: iconst_2
      20: bipush        10
      22: invokestatic  #18                 // Method java/lang/Integer.valueOf:(I)Ljava/lang/Integer;
      25: aastore
      26: dup
      27: iconst_3
      28: bipush        20
      30: invokestatic  #18                 // Method java/lang/Integer.valueOf:(I)Ljava/lang/Integer;
      33: aastore
      34: invokestatic  #22                 // InterfaceMethod java/util/stream/Stream.of:([Ljava/lang/Object;)Ljava/util/stream/Stream;
      37: astore_1
      38: aload_1
      39: invokedynamic #31,  0             // InvokeDynamic #0:test:()Ljava/util/function/Predicate;
      44: invokeinterface #32,  2           // InterfaceMethod java/util/stream/Stream.filter:(Ljava/util/function/Predicate;)Ljava/util/stream/Stream;
      49: invokedynamic #39,  0             // InvokeDynamic #1:apply:()Ljava/util/function/Function;
      54: invokeinterface #40,  2           // InterfaceMethod java/util/stream/Stream.map:(Ljava/util/function/Function;)Ljava/util/stream/Stream;
      59: ldc           #44                 // String ,
      61: invokestatic  #46                 // Method java/util/stream/Collectors.joining:(Ljava/lang/CharSequence;)Ljava/util/stream/Collector;
      64: invokeinterface #52,  2           // InterfaceMethod java/util/stream/Stream.collect:(Ljava/util/stream/Collector;)Ljava/lang/Object;
      69: checkcast     #56                 // class java/lang/String
      72: astore_2
      73: getstatic     #58                 // Field java/lang/System.out:Ljava/io/PrintStream;
      76: new           #64                 // class java/lang/StringBuilder
      79: dup
      80: ldc           #66                 // String Lambda:
      82: invokespecial #68                 // Method java/lang/StringBuilder."<init>":(Ljava/lang/String;)V
      85: aload_2
      86: invokevirtual #71                 // Method java/lang/StringBuilder.append:(Ljava/lang/String;)Ljava/lang/StringBuilder;
      89: invokevirtual #75                 // Method java/lang/StringBuilder.toString:()Ljava/lang/String;
      92: invokevirtual #79                 // Method java/io/PrintStream.println:(Ljava/lang/String;)V
      95: iconst_4
      96: anewarray     #16                 // class java/lang/Integer
      99: dup
     100: iconst_0
     101: iconst_2
     102: invokestatic  #18                 // Method java/lang/Integer.valueOf:(I)Ljava/lang/Integer;
     105: aastore
     106: dup
     107: iconst_1
     108: iconst_5
     109: invokestatic  #18                 // Method java/lang/Integer.valueOf:(I)Ljava/lang/Integer;
     112: aastore
     113: dup
     114: iconst_2
     115: bipush        10
     117: invokestatic  #18                 // Method java/lang/Integer.valueOf:(I)Ljava/lang/Integer;
     120: aastore
     121: dup
     122: iconst_3
     123: bipush        20
     125: invokestatic  #18                 // Method java/lang/Integer.valueOf:(I)Ljava/lang/Integer;
     128: aastore
     129: invokestatic  #22                 // InterfaceMethod java/util/stream/Stream.of:([Ljava/lang/Object;)Ljava/util/stream/Stream;
     132: astore_3
     133: aload_3
     134: new           #84                 // class de/viadee/lambda/codebeispiele/sprachAenderungen/LambdaVsInnerClass2$1InnerClass
     137: dup
     138: bipush        10
     140: invokestatic  #18                 // Method java/lang/Integer.valueOf:(I)Ljava/lang/Integer;
     143: invokespecial #86                 // Method de/viadee/lambda/codebeispiele/sprachAenderungen/LambdaVsInnerClass2$1InnerClass."<init>":(Ljava/lang/Integer;)V
     146: invokeinterface #32,  2           // InterfaceMethod java/util/stream/Stream.filter:(Ljava/util/function/Predicate;)Ljava/util/stream/Stream;
     151: invokedynamic #89,  0             // InvokeDynamic #2:apply:()Ljava/util/function/Function;
     156: invokeinterface #40,  2           // InterfaceMethod java/util/stream/Stream.map:(Ljava/util/function/Function;)Ljava/util/stream/Stream;
     161: ldc           #44                 // String ,
     163: invokestatic  #46                 // Method java/util/stream/Collectors.joining:(Ljava/lang/CharSequence;)Ljava/util/stream/Collector;
     166: invokeinterface #52,  2           // InterfaceMethod java/util/stream/Stream.collect:(Ljava/util/stream/Collector;)Ljava/lang/Object;
     171: pop
     172: getstatic     #58                 // Field java/lang/System.out:Ljava/io/PrintStream;
     175: new           #64                 // class java/lang/StringBuilder
     178: dup
     179: ldc           #90                 // String InnerClass:
     181: invokespecial #68                 // Method java/lang/StringBuilder."<init>":(Ljava/lang/String;)V
     184: aload_2
     185: invokevirtual #71                 // Method java/lang/StringBuilder.append:(Ljava/lang/String;)Ljava/lang/StringBuilder;
     188: invokevirtual #75                 // Method java/lang/StringBuilder.toString:()Ljava/lang/String;
     191: invokevirtual #79                 // Method java/io/PrintStream.println:(Ljava/lang/String;)V
     194: return
}
